clams/__init__.py
clams/vis/__init__.py
clams/vis/feature_importance.py
clams/vis/plotComponents1D.py
clams/vis/plotComponents2D.py
clams/vis/plotComponents3D.py
clams/vis/plt2base64.py
clams/vis/unsupervised_dimension_reductions.py
pyCLAMs-0.4.1.dist-info/LICENCE
pyCLAMs-0.4.1.dist-info/METADATA
pyCLAMs-0.4.1.dist-info/WHEEL
pyCLAMs-0.4.1.dist-info/top_level.txt
pyCLAMs-0.4.1.dist-info/RECORD
